codemod_tox/__init__.py
codemod_tox/_version.py
codemod_tox/base.py
codemod_tox/conditional.py
codemod_tox/env.py
codemod_tox/envlist.py
codemod_tox/exceptions.py
codemod_tox/options.py
codemod_tox/parse.py
codemod_tox/py.typed
codemod_tox/utils.py
codemod_tox-0.5.0.dist-info/LICENSE
codemod_tox-0.5.0.dist-info/METADATA
codemod_tox-0.5.0.dist-info/WHEEL
codemod_tox-0.5.0.dist-info/top_level.txt
codemod_tox-0.5.0.dist-info/RECORD
