Metadata-Version: 2.1
Name: codemod-tox
Version: 0.5.0
Summary: Utilities for editing tox.ini
Home-page: https://github.com/advice-animal/codemod-tox
Author: Tim Hatch
Author-email: tim@timhatch.com
License: MIT
Requires-Python: >=3.7
License-File: LICENSE
Provides-Extra: dev
Requires-Dist: black ==24.2.0 ; extra == 'dev'
Requires-Dist: checkdeps ==0.9.0 ; extra == 'dev'
Requires-Dist: flake8 ==7.0.0 ; extra == 'dev'
Requires-Dist: mypy ==1.8.0 ; extra == 'dev'
Requires-Dist: tox ==4.12.1 ; extra == 'dev'
Requires-Dist: twine ==4.0.2 ; extra == 'dev'
Requires-Dist: ufmt ==2.5.1 ; extra == 'dev'
Requires-Dist: usort ==1.0.7 ; extra == 'dev'
Requires-Dist: wheel ==0.42.0 ; extra == 'dev'
Provides-Extra: test
Requires-Dist: coverage >=6 ; extra == 'test'
Requires-Dist: pytest ; extra == 'test'
Requires-Dist: pytest-cov ; extra == 'test'
